MANIFEST.in
README.txt
setup.py
BuffetXSLT.egg-info/PKG-INFO
BuffetXSLT.egg-info/SOURCES.txt
BuffetXSLT.egg-info/entry_points.txt
BuffetXSLT.egg-info/not-zip-safe
BuffetXSLT.egg-info/top_level.txt
buffet_test/test.py
buffet_test/templates/another.xsl
buffet_test/templates/index.xsl
buffetxslt/__init__.py
buffetxslt/xsltsupport.py
