Metadata-Version: 1.0
Name: BuffetXSLT
Version: 0.2
Summary: XSLT templating plugin
Home-page: http://projects.dowski.com/projects/buffetxslt
Author: Sylvain Hellegouarch, Christian Wyglendowski
Author-email: christian@dowski.com
License: MIT
Platform: UNKNOWN
